nsetools/__init__.py
nsetools/bases.py
nsetools/cleaners.py
nsetools/datemgr.py
nsetools/downloader.py
nsetools/errors.py
nsetools/nse.py
nsetools/ua.py
nsetools/urls.py
nsetools/utils.py
nsetools-2.0.0.dist-info/LICENSE
nsetools-2.0.0.dist-info/METADATA
nsetools-2.0.0.dist-info/WHEEL
nsetools-2.0.0.dist-info/top_level.txt
nsetools-2.0.0.dist-info/RECORD
