Metadata-Version: 2.2
Name: nsetools
Version: 2.0.0
Summary: Python library for extracting realtime data from National Stock Exchange
Home-page: http://vsjha18.github.com/nsetools
Author: Vivek Jha
Author-email: Vivek Jha <vsjha18@gmail.com>
License: MIT
Project-URL: Homepage, http://vsjha18.github.com/nsetools
Keywords: nse,quote,market
License-File: LICENSE
Requires-Dist: six
Requires-Dist: dateutils
Requires-Dist: requests
Dynamic: author
Dynamic: home-page
